FileEssentials/__init__.py
FileEssentials-1.1.3.dist-info/LICENSE
FileEssentials-1.1.3.dist-info/METADATA
FileEssentials-1.1.3.dist-info/WHEEL
FileEssentials-1.1.3.dist-info/top_level.txt
FileEssentials-1.1.3.dist-info/RECORD
