Metadata-Version: 2.1
Name: FileEssentials
Version: 1.1.3
Summary: File Essentials is a package that contains all of the necessary functions for using files
Home-page: http://github.com/DaRubyMiner360/FileEssentials
Author: DaRubyMiner360
Author-email: darubyminer360@gmail.com
License: UNKNOWN
Platform: UNKNOWN
Classifier: Programming Language :: Python :: 3
Classifier: License :: OSI Approved :: MIT License
Classifier: Operating System :: OS Independent
Requires-Python: >=3.6
